nob/__init__.py
nob/nob.py
nob/path.py
nob/tools.py
nob/core/__init__.py
nob/core/path.py
nob/core/tree.py
nob-0.8.1.dist-info/LICENSE
nob-0.8.1.dist-info/METADATA
nob-0.8.1.dist-info/WHEEL
nob-0.8.1.dist-info/entry_points.txt
nob-0.8.1.dist-info/top_level.txt
nob-0.8.1.dist-info/RECORD
