Metadata-Version: 2.1
Name: nob
Version: 0.8.1
Summary: Nested OBject manipulations
Home-page: https://gitlab.com/cerfacs/nob
Author-email: lapeyre@cerfacs.fr
License: UNKNOWN
Keywords: JSON,YAML,Nested Object
Platform: UNKNOWN
Classifier: Programming Language :: Python :: 3.8
Classifier: Programming Language :: Python :: 3.9
Provides-Extra: docs
Requires-Dist: sphinx ; extra == 'docs'
Requires-Dist: myst-parser ; extra == 'docs'
Provides-Extra: test
Requires-Dist: numpy ; extra == 'test'
